darq_ui-0.0.5.dist-info/METADATA
darq_ui-0.0.5.dist-info/WHEEL
darq_ui-0.0.5.dist-info/entry_points.txt
darq_ui-0.0.5.dist-info/licenses/LICENSE
darq_ui/__init__.py
darq_ui/darq.py
darq_ui/handlers.py
darq_ui/integration/aiohttp.py
darq_ui/integration/fastapi.py
darq_ui/static/assets/favicon-BSE-TIUP.ico
darq_ui/static/assets/index-DV_5qxoM.js
darq_ui/static/assets/vendor-DwS7OE0o.js
darq_ui/static/index.html
darq_ui/utils.py
darq_ui-0.0.5.dist-info/RECORD
