Metadata-Version: 2.1
Name: darq-ui
Version: 0.0.5
Summary: A UI for darq
Author-Email: "m.kindritskiy" <kindritskiy.m@gmail.com>
License: BSD-3-Clause
Classifier: Development Status :: 5 - Production/Stable
Classifier: Intended Audience :: Developers
Classifier: License :: OSI Approved :: BSD License
Classifier: Operating System :: OS Independent
Classifier: Programming Language :: Python
Classifier: Programming Language :: Python :: 3.10
Classifier: Programming Language :: Python :: 3.11
Classifier: Programming Language :: Python :: 3.12
Classifier: Programming Language :: Python :: 3 :: Only
Classifier: Topic :: Software Development :: Libraries :: Python Modules
Project-URL: Repository, https://github.com/evo-company/darq_ui
Project-URL: Homepage, https://github.com/evo-company/darq_ui
Requires-Python: >=3.10
Requires-Dist: darq>=0.11.2
Requires-Dist: pydantic>=2.9.2
Provides-Extra: fastapi
Requires-Dist: fastapi>=0.115.0; extra == "fastapi"
Provides-Extra: aiohttp
Requires-Dist: aiohttp>=3.10.10; extra == "aiohttp"
Provides-Extra: dev
Requires-Dist: mypy>=1.11.2; extra == "dev"
Requires-Dist: ruff>=0.6.9; extra == "dev"
